BrainFuckPlusInterpreter/BrainFuckPlusInterpreter.py
BrainFuckPlusInterpreter/setup.py
sqlite_help_functions/__init__.py
sqlite_help_functions/main.py
sqlite_help_functions/setup.py
this_is_my_package_called_password/my_password.py
this_is_my_package_called_password/setup.py
BrainFuckPlusInterpreter-3.0.0.dist-info/METADATA
BrainFuckPlusInterpreter-3.0.0.dist-info/WHEEL
BrainFuckPlusInterpreter-3.0.0.dist-info/top_level.txt
BrainFuckPlusInterpreter-3.0.0.dist-info/RECORD
