Metadata-Version: 2.1
Name: BrainFuckPlusInterpreter
Version: 3.0.0
Summary: BrainFuckPlusInterpreter: Exactly what it sounds like
Home-page: https://github.com/TvoozMagnificent/BrainFuckPlusInterpreter
Author: TvoozMagnificent
Author-email: luchang1106@icloud.com
License: MIT
Platform: UNKNOWN
Classifier: License :: OSI Approved :: MIT License
Classifier: Programming Language :: Python :: 3
Classifier: Programming Language :: Python :: 3.7
